CHANGES.txt
MANIFEST.in
README.md
setup.py
django_workflow.egg-info/PKG-INFO
django_workflow.egg-info/SOURCES.txt
django_workflow.egg-info/dependency_links.txt
django_workflow.egg-info/requires.txt
django_workflow.egg-info/top_level.txt
workflow/__init__.py
workflow/admin.py
workflow/apps.py
workflow/dot.py
workflow/fields.py
workflow/forms.py
workflow/managers.py
workflow/models.py
workflow/signals.py
workflow/views.py
workflow/migrations/0001_squashed_0007_20160803_0939.py
workflow/migrations/__init__.py