Metadata-Version: 1.1
Name: django-workflow
Version: 1.6
Summary: Workflow editor for Django
Home-page: https://github.com/simplyopen-it/django-workflow
Author: SimplyOpen
Author-email: info@simplyopen.org
License: UNKNOWN
Platform: UNKNOWN
Classifier: Development Status :: 5 - Production/Stable
Classifier: Framework :: Django
Classifier: Intended Audience :: Developers
Classifier: Operating System :: OS Independent
Classifier: Topic :: Software Development
